httpie_akamai.py
httpie_akamai-0.1.5.dist-info/DESCRIPTION.rst
httpie_akamai-0.1.5.dist-info/METADATA
httpie_akamai-0.1.5.dist-info/RECORD
httpie_akamai-0.1.5.dist-info/WHEEL
httpie_akamai-0.1.5.dist-info/entry_points.txt
httpie_akamai-0.1.5.dist-info/metadata.json
httpie_akamai-0.1.5.dist-info/top_level.txt
