Metadata-Version: 2.0
Name: httpie-akamai
Version: 0.1.5
Summary: Akamai utility plugins for HTTPie.
Home-page: https://github.com/matteck/httpie-akamai
Author: Matt Eckhaus
Author-email: matt@eckha.us
License: BSD
Download-URL: https://github.com/matteck/httpie-akamai
Platform: UNKNOWN
Classifier: Development Status :: 4 - Beta
Classifier: Programming Language :: Python
Classifier: Programming Language :: Python :: 2
Classifier: Programming Language :: Python :: 2.6
Classifier: Programming Language :: Python :: 2.7
Classifier: Programming Language :: Python :: 3
Classifier: Programming Language :: Python :: 3.3
Classifier: Programming Language :: Python :: 3.4
Classifier: Programming Language :: Python :: 3.5
Classifier: Intended Audience :: System Administrators
Classifier: Intended Audience :: Developers
Classifier: Environment :: Plugins
Classifier: License :: OSI Approved :: BSD License
Classifier: Topic :: Internet :: WWW/HTTP
Classifier: Topic :: Utilities
Requires-Dist: httpie (>=0.9.0)
Requires-Dist: requests
